linkstatus/__init__.py
linkstatus/linkstatus.py
linkstatus/parser.py
linkstatus-1.0.dist-info/LICENSE
linkstatus-1.0.dist-info/METADATA
linkstatus-1.0.dist-info/WHEEL
linkstatus-1.0.dist-info/entry_points.txt
linkstatus-1.0.dist-info/top_level.txt
linkstatus-1.0.dist-info/RECORD
