Metadata-Version: 2.1
Name: linkstatus
Version: 1.0
Summary: Simple text/ markdown links status checker
Home-page: https://github.com/pythonpune/linkstatus
Author: Nikhil Dhandre
Author-email: nik.digitronik@live.com
License: UNKNOWN
Keywords: linkstatus,linkchecker,link-checker,markdown,text,linklint,link
Platform: UNKNOWN
Classifier: Natural Language :: English
Classifier: Programming Language :: Python :: 3.6
Classifier: Programming Language :: Python :: 3.7
Classifier: Programming Language :: Python :: 3.8
Classifier: Intended Audience :: End Users/Desktop
Classifier: Intended Audience :: Developers
Classifier: Environment :: Console
Classifier: License :: OSI Approved :: GNU General Public License v3 (GPLv3)
Requires-Python: >=3.6
Requires-Dist: click
Requires-Dist: requests
Requires-Dist: urlextract
